{"nodes": [{"id": "remaining_test", "label": "remaining.test.ts", "file_type": "code", "source_file": "/Users/rahilsinghi/Desktop/brain/tests/seed/transforms/remaining.test.ts", "source_location": "L1"}], "edges": [{"source": "remaining_test", "target": "vitest", "relation": "imports_from", "confidence": "EXTRACTED", "source_file": "/Users/rahilsinghi/Desktop/brain/tests/seed/transforms/remaining.test.ts", "source_location": "L1", "weight": 1.0}, {"source": "remaining_test", "target": "skills_js", "relation": "imports_from", "confidence": "EXTRACTED", "source_file": "/Users/rahilsinghi/Desktop/brain/tests/seed/transforms/remaining.test.ts", "source_location": "L2", "weight": 1.0}, {"source": "remaining_test", "target": "companies_js", "relation": "imports_from", "confidence": "EXTRACTED", "source_file": "/Users/rahilsinghi/Desktop/brain/tests/seed/transforms/remaining.test.ts", "source_location": "L3", "weight": 1.0}, {"source": "remaining_test", "target": "positioning_js", "relation": "imports_from", "confidence": "EXTRACTED", "source_file": "/Users/rahilsinghi/Desktop/brain/tests/seed/transforms/remaining.test.ts", "source_location": "L4", "weight": 1.0}, {"source": "remaining_test", "target": "stories_js", "relation": "imports_from", "confidence": "EXTRACTED", "source_file": "/Users/rahilsinghi/Desktop/brain/tests/seed/transforms/remaining.test.ts", "source_location": "L5", "weight": 1.0}, {"source": "remaining_test", "target": "answers_js", "relation": "imports_from", "confidence": "EXTRACTED", "source_file": "/Users/rahilsinghi/Desktop/brain/tests/seed/transforms/remaining.test.ts", "source_location": "L6", "weight": 1.0}, {"source": "remaining_test", "target": "tracking_js", "relation": "imports_from", "confidence": "EXTRACTED", "source_file": "/Users/rahilsinghi/Desktop/brain/tests/seed/transforms/remaining.test.ts", "source_location": "L7", "weight": 1.0}, {"source": "remaining_test", "target": "schemas_js", "relation": "imports_from", "confidence": "EXTRACTED", "source_file": "/Users/rahilsinghi/Desktop/brain/tests/seed/transforms/remaining.test.ts", "source_location": "L8", "weight": 1.0}]}